useful_graphs/__init__.py
useful_graphs/confusion_matrix.py
useful_graphs/evaluation.py
useful_graphs-0.1.2.dist-info/DESCRIPTION.rst
useful_graphs-0.1.2.dist-info/METADATA
useful_graphs-0.1.2.dist-info/RECORD
useful_graphs-0.1.2.dist-info/WHEEL
useful_graphs-0.1.2.dist-info/metadata.json
useful_graphs-0.1.2.dist-info/top_level.txt
