Metadata-Version: 2.0
Name: useful-graphs
Version: 0.1.2
Summary: useful graphs
Home-page: https://github.com/yuuuuwwww/useful_graphs
Author: Yusuke Sakai
Author-email: my.gosh.love.ya@gmail.com
License: MIT
Keywords: graphs
Platform: UNKNOWN
Classifier: Development Status :: 1 - Planning
Requires-Dist: matplotlib (>=1.3.1)
Requires-Dist: numpy (>=1.13.1)
